{
	"backtraceGraph" : 
	{
		"commands" : 
		[
			"install"
		],
		"files" : 
		[
			"FluentUI/CMakeLists.txt"
		],
		"nodes" : 
		[
			{
				"file" : 0
			},
			{
				"command" : 0,
				"file" : 0,
				"line" : 230,
				"parent" : 0
			}
		]
	},
	"installers" : 
	[
		{
			"backtrace" : 1,
			"component" : "Unspecified",
			"destination" : "C:/Program Files (x86)/my_code_2024_6_13.1/imports",
			"paths" : 
			[
				"D:/AppData/Qt6/Qt/6.7.0/msvc2019_64//qml/FluentUI"
			],
			"type" : "directory"
		}
	],
	"paths" : 
	{
		"build" : "FluentUI",
		"source" : "FluentUI"
	}
}
